{
    "AX": {
        "error": 0.0036827130041205813,
        "error_type": "SEM",
        "filter_outliers_dict": {
            "filter_outliers": true,
            "iterations": 1,
            "std_devs": 2
        },
        "fit": "Average",
        "value": -0.014279369068328126
    },
    "CDD": {
        "error": 2.052976176231318e-06,
        "error_type": "SEM",
        "filter_outliers_dict": {
            "filter_outliers": false,
            "iterations": 1,
            "std_devs": 2
        },
        "fit": "Average",
        "value": -1.884337353491677e-05
    },
    "H1": {
        "error": 0.008968687381110575,
        "error_type": "SEM",
        "filter_outliers_dict": {
            "filter_outliers": true,
            "iterations": 1,
            "std_devs": 2
        },
        "fit": "Average",
        "value": -0.14047707823731378
    },
    "H2": {
        "error": 0.007678053539811018,
        "error_type": "SEM",
        "filter_outliers_dict": {
            "filter_outliers": true,
            "iterations": 1,
            "std_devs": 2
        },
        "fit": "Average",
        "value": -0.09209008751860809
    },
    "L1": {
        "error": 0.0068350555337185915,
        "error_type": "SEM",
        "filter_outliers_dict": {
            "filter_outliers": true,
            "iterations": 1,
            "std_devs": 2
        },
        "fit": "Average",
        "value": -0.016637505876622587
    },
    "L2": {
        "error": 0.0038121785364462523,
        "error_type": "SEM",
        "filter_outliers_dict": {
            "filter_outliers": false,
            "iterations": 1,
            "std_devs": 2
        },
        "fit": "Average",
        "value": -0.0006818097279436358
    }
}