{
    "Ar36": {
        "error": 0.00045652656546731106,
        "error_type": "SEM",
        "filter_outliers_dict": {
            "filter_outliers": true,
            "iterations": 1,
            "std_devs": 2
        },
        "fit": "Parabolic",
        "value": 0.08011101287262404
    },
    "Ar37": {
        "error": 0.004151681424678512,
        "error_type": "SEM",
        "filter_outliers_dict": {
            "filter_outliers": true,
            "iterations": 1,
            "std_devs": 2
        },
        "fit": "Linear",
        "value": 0.014196350167845201
    },
    "Ar38": {
        "error": 0.0088767922138192,
        "error_type": "SEM",
        "filter_outliers_dict": {
            "filter_outliers": true,
            "iterations": 1,
            "std_devs": 2
        },
        "fit": "Linear",
        "value": 0.007916224680887905
    },
    "Ar39": {
        "error": 0.006333830409365013,
        "error_type": "SEM",
        "filter_outliers_dict": {
            "filter_outliers": true,
            "iterations": 1,
            "std_devs": 2
        },
        "fit": "Parabolic",
        "value": 0.07994230508781336
    },
    "Ar40": {
        "error": 0.029303107952874923,
        "error_type": "SEM",
        "filter_outliers_dict": {
            "filter_outliers": true,
            "iterations": 1,
            "std_devs": 2
        },
        "fit": "Parabolic",
        "value": 19.404374863109716
    },
    "PM41": {
        "error": 0.010115437907621795,
        "error_type": null,
        "filter_outliers_dict": {
            "filter_outliers": false,
            "iterations": 1,
            "std_devs": 2
        },
        "fit": "linear",
        "value": 0.04275331860831662
    }
}